LICENSE.txt
MANIFEST.in
README.md
pyproject.toml
setup.cfg
setup.py
src/mkdocs_pom_parser_plugin/__init__.py
src/mkdocs_pom_parser_plugin/parser.py
src/mkdocs_pom_parser_plugin/plugin.py
src/mkdocs_pom_parser_plugin.egg-info/PKG-INFO
src/mkdocs_pom_parser_plugin.egg-info/SOURCES.txt
src/mkdocs_pom_parser_plugin.egg-info/dependency_links.txt
src/mkdocs_pom_parser_plugin.egg-info/entry_points.txt
src/mkdocs_pom_parser_plugin.egg-info/requires.txt
src/mkdocs_pom_parser_plugin.egg-info/top_level.txt