Metadata-Version: 2.1
Name: mkdocs-pom-parser-plugin
Version: 1.0.3
Summary: A simple `mkdocs` plugin which parsers a `pom.xml` file and exposes it's values as template environment variables
Home-page: https://github.com/steve-todorov/mkdocs-pom-parser-plugin
Author: Steve Todorov
Author-email: steve.todorov@carlspring.com
License: UNKNOWN
Project-URL: Bug Reports, https://github.com/steve-todorov/mkdocs-pom-parser-plugin/issues
Project-URL: Say Thanks!, https://github.com/steve-todorov/mkdocs-pom-parser-plugin
Project-URL: Source, https://github.com/steve-todorov/mkdocs-pom-parser-plugin
Keywords: mkdocs,maven,pom,parser,plugin
Platform: UNKNOWN
Classifier: Development Status :: 5 - Production/Stable
Classifier: Intended Audience :: Developers
Classifier: Topic :: Software Development :: Build Tools
Classifier: License :: OSI Approved :: MIT License
Classifier: Programming Language :: Python :: 3
Classifier: Programming Language :: Python :: 3.5
Classifier: Programming Language :: Python :: 3.6
Classifier: Programming Language :: Python :: 3.7
Classifier: Programming Language :: Python :: 3.8
Classifier: Programming Language :: Python :: 3 :: Only
Requires-Python: >=3.5, <4
Provides-Extra: dev
Provides-Extra: test
